ctrshif/AttributeFile.py
ctrshif/CustomExceptions.py
ctrshif/RenderingEngine.py
ctrshif/TemplateFile.py
ctrshif/__init__.py
ctrshif-0.0.2.data/scripts/ctrshif
ctrshif-0.0.2.dist-info/DESCRIPTION.rst
ctrshif-0.0.2.dist-info/METADATA
ctrshif-0.0.2.dist-info/RECORD
ctrshif-0.0.2.dist-info/WHEEL
ctrshif-0.0.2.dist-info/metadata.json
ctrshif-0.0.2.dist-info/top_level.txt
