Metadata-Version: 2.0
Name: ctrshif
Version: 0.0.2
Summary: Find and replace command line tool
Home-page: https://github.com/romerojunior/ctrshif
Author: Romero Galiza Jr
Author-email: rgaliza@schubergphilis.com
License: Apache License Version 2.0
Download-URL: https://github.com/romerojunior/ctrshif/archive/0.0.2.tar.gz
Keywords: templating,configparse
Platform: Any
Classifier: Programming Language :: Python :: 3
Classifier: License :: OSI Approved :: Apache Software License
Classifier: Operating System :: OS Independent
Classifier: Topic :: Text Processing
Requires-Dist: colorama
